{
    "filename": "38130c34-225a-492b-ae34-ffe14fe53654.png",
    "category": "National Library Board Singapore",
    "tags": [
        "Kampong/Village",
        "Residential Area",
        "Plantation/Forestry Area",
        "Crops",
        "Port",
        "River",
        "Maritime Route",
        "Jungle/Wooded Area",
        "Mountain/Volcano",
        "Reef",
        "Shoal"
    ],
    "description": "\"An early map of the island of Borneo, depicting the natural landscape of mountains, forests, rivers and shoals, and also evidence of human habitation with houses representing settlements, and a port and shipping route along the northern coast.\"",
    "permalink": "https://historicalmaps.yale-nus.edu.sg/catalog/nlb__B26056123C",
    "year": "1602",
    "title": "\"Borneo Insula / Beniamin Wright c\u00e6lator.\"",
    "lat": "0.7627",
    "lng": "114.5874"
}