{
    "filename": "3955bdd9-4288-465d-ac8c-e1fcc5028e32.png",
    "category": "National Library Board Singapore",
    "tags": [
        "River",
        "Civic/Metropolitan Border",
        "Reef",
        "Shoal"
    ],
    "description": "\"This mid-17th century map of Asia is illustrated with drawings of Asian people wearing traditional clothing, including a man and woman from Java in Southeast Asia. There are also drawings and plans of important Asian cities.\"",
    "permalink": "https://historicalmaps.yale-nus.edu.sg/catalog/nlb__B26056028G",
    "year": "1660",
    "title": "\"Asi\u00e6 nova descriptio / t'Amsterdam by Frederick de Wit in de Kalverstraet in de Witte Paskaert.\"",
    "lat": "26.0755",
    "lng": "84.1993"
}