{
    "filename": "42bafeaa-ad50-436a-aa32-6ec763bd7996.png",
    "category": "National Library Board Singapore",
    "tags": [
        "River",
        "Regional Border",
        "Reef",
        "Shoal",
        "Wind Data"
    ],
    "description": "\"The arrows on this map show the direction of the seasonal monsoons of Southeast Asia during the late 18th century. Each arrow has a label in French, indicating the month. The hatched sea areas are where the winds always blow in the same direction.\"",
    "permalink": "https://historicalmaps.yale-nus.edu.sg/catalog/nlb__B26055995H",
    "year": "1771",
    "title": "\"Carte hydro-geo-graphique des Indes orientales, en deca\u0327 et au dela du Gange avec leur archipel / dressee\u0301 et assujettie aux observations astronomiques, par M. Bonne, hydrographe du Roi.\"",
    "lat": "1.0709",
    "lng": "118.1250"
}