{
    "filename": "50e30e34-a052-44e1-b173-e7b969ac6c95.png",
    "category": "National Library Board Singapore",
    "tags": [
        "Plantation/Forestry Area",
        "Crops",
        "Jungle/Wooded Area",
        "Mountain/Volcano",
        "Shoal"
    ],
    "description": "\"Although mainly a navigation map\u2014with a rhumbline network and elevations of mountains\u2014there are also many terrestrial details shown, such as settlements and mountains. The inset map of Hoeamohel details plantations and the cultivation of nut crops.\"",
    "permalink": "https://historicalmaps.yale-nus.edu.sg/catalog/nlb__B26055921H",
    "year": "1726",
    "title": "\"De landvoogdy van Amboina met de elf onderhoorige eylanden\"",
    "lat": "-0.6498",
    "lng": "128.9246"
}