{
    "filename": "7e3b20e6-1c94-4597-829d-6a4ce5340860.png",
    "category": "National Library Board Singapore",
    "tags": [
        "River",
        "Population Density",
        "Regional Border",
        "Mountain/Volcano"
    ],
    "description": "\"This map of Asia was published by The Society for the Diffusion of Useful Knowledge in the mid-19th century. It includes a list of the number of people living in each Asian region, with the total population of Asia listed as 630 million.\"",
    "permalink": "https://historicalmaps.yale-nus.edu.sg/catalog/nlb__050000154",
    "year": "1840",
    "title": "\"Asia / published under the superintendence of the Society for the Diffusion of Useful Knowledge ; engraved by J. & C. Walker.\"",
    "lat": "33.2529",
    "lng": "88.7695"
}