{
    "filename": "bdae9353-d444-4ad3-9554-996c325b6801.png",
    "category": "National Library Board Singapore",
    "tags": [
        "River",
        "National Border",
        "Regional Border",
        "Mountain/Volcano"
    ],
    "description": "\"A 19th century map of mainland Southeast Asia, showing the ancient kingdoms of the Birman Empire (roughly modern Myanmar), Malaya (Malaysia), Siam (Thailand), Cochin China and Tonquin (Vietnam), and the Anamese Empire (Cambodia and Laos).\"",
    "permalink": "https://historicalmaps.yale-nus.edu.sg/catalog/nlb__050000145",
    "year": "1834",
    "title": "\"Birman Empire & countries south east of the Ganges / drawn & engraved by J. Dower.\"",
    "lat": "13.9346",
    "lng": "99.9096"
}