{
    "filename": "beinecke__1115323.tif.png",
    "category": "Beinecke Library Yale University",
    "tags": [
        "Kampong/Village",
        "Residential Area",
        "Economic Animals",
        "Crops",
        "Plantation/Forestry Area",
        "Wild Animal"
    ],
    "description": "\"This early map of Sumatra (labelled \u2018Taprobana\u2019) features many illustrations. In the sea, there are ships, fish and sea monsters, while on land, plantations, agricultural workers, a shepherd and wooden buildings highlight the economy of the island.\"",
    "permalink": "https://historicalmaps.yale-nus.edu.sg/catalog/beinecke__1115323",
    "year": "1565",
    "title": "\"Sumatra\"",
    "lat": "0.4011",
    "lng": "102.3926"
}