{
    "filename": "beinecke__1024529.tif.png",
    "category": "Beinecke Library Yale University",
    "tags": [
        "River"
    ],
    "description": "\"This early 19th century map depicts the regions of Asia by colour. The continental regions are green, while the archipelago regions are red, except for New Guinea which is yellow.\"",
    "permalink": "https://historicalmaps.yale-nus.edu.sg/catalog/beinecke__1024529",
    "year": "1809",
    "title": "\"Asia.   Engraved   for   Evans's   Geographical   Grammar\"",
    "lat": "22.4285",
    "lng": "106.5234"
}