{
    "filename": "bodleian__Bodleian_0038.tif.png",
    "category": "Bodleian Libraries University of Oxford",
    "tags": [
        "Bodleian Libraries University of Oxford"
    ],
    "description": "\"The residency of Soerabaja, East Java, featuring crops (coffee, coconut, sugarcane, rice, alang-alang, bamboo) and fishing ponds. Three inset maps: a triangulation map; a map of distances between settlements by types of transport; Bawean Island.\"",
    "permalink": "https://historicalmaps.yale-nus.edu.sg/catalog/bodleian__0283",
    "year": "1875",
    "title": "\"A map shewing the various routes proposed for connecting China with India and Europe through Burmah and developing the trade of Eastern Bengal, Burmah and China [cartographic material].\"",
    "lat": "0",
    "lng": "0"
}