{
    "filename": "ca1a1be9-a344-4f78-aaf8-55a1fe5a52a4.png",
    "category": "National Library Board Singapore",
    "tags": [
        "Kampong/Village",
        "Crops",
        "Plantation/Forestry Area",
        "River",
        "Bathymetry",
        "Jungle/Wooded Area",
        "Mountain/Volcano",
        "Shoal",
        "Reef"
    ],
    "description": "\"On this map of Bali (and parts of Java and Lombok), mountains, trees, fields and settlements are shown pictorially. The coasts are marked with shoals (dots), reefs (crosses), bathymetry (sea depth, in figures) and anchor points (anchor symbols).\"",
    "permalink": "https://historicalmaps.yale-nus.edu.sg/catalog/nlb__B26055991D",
    "year": "1726",
    "title": "\"Kaart van het Eyland Bali\"",
    "lat": "-0.5379",
    "lng": "115.0159"
}