{
    "filename": "e937d5f6-6b2a-428c-ac04-8bcbaba536f1.png",
    "category": "National Library Board Singapore",
    "tags": [
        "River",
        "Race/Ethnicity",
        "Regional Border",
        "Mountain/Volcano",
        "Reef",
        "Shoal"
    ],
    "description": "\"This late 18th century map features a number of labels describing the local populations, including the Kemoys ('Savage People') of the mountains of Cokin China (Vietnam), the Biayos of Borneo, and the 'Wild People' of the mountains of Pegu (Myanmar).\"",
    "permalink": "https://historicalmaps.yale-nus.edu.sg/catalog/nlb__B26055915K",
    "year": "1794",
    "title": "\"Asia and its islands according to D'Anville : divided into empires, kingdoms, states, regions, &ca. : with the European possessions and settlements in the East Indies and an exact delineation of all the discoveries made in the Eastern parts by the English under Captn. Cook\"",
    "lat": "26.9950",
    "lng": "93.3399"
}