{
    "filename": "e9bf6ef0-a97e-42cb-8b33-49890b95bee1.png",
    "category": "National Library Board Singapore",
    "tags": [
        "Kampong/Village",
        "Residential Area",
        "Military Fort",
        "Mountain/Volcano",
        "Jungle/Wooded Area"
    ],
    "description": "\"Taken from Benedetto Bordone's \u2018Isolario [The Book of Islands]\u2019, these pages contain two maps: one of Sumatra (\u2018Iaua Minore\u2019), and one of a group of five unknown islands (Locaz is thought to possibly be Thailand).\"",
    "permalink": "https://historicalmaps.yale-nus.edu.sg/catalog/nlb__B26056162F",
    "year": "1547",
    "title": "\"[Iava minore and map of Necumera, Locaz, Patera, Botegon Mangama]\"",
    "lat": "0.2837",
    "lng": "101.2939"
}