{
    "filename": "hdl%3A1887.1%2Fitem%3A3181776.png",
    "category": "Leiden University Libraries",
    "tags": [
        "Military Fort",
        "Kampong/Village",
        "Port",
        "Bathymetry",
        "Maritime Route",
        "Mountain/Volcano",
        "Jungle/Wooded Area",
        "Shoal",
        "Reef"
    ],
    "description": "\"There is a port at the south of this map of the C\u00f4n \u0110\u1ea3o archipelago (Vietnam), and notes giving details such as a suitable location to careen ships (turning a ship on its side for cleaning or repair). A ruined English fort is also marked.\"",
    "permalink": "https://historicalmaps.yale-nus.edu.sg/catalog/ld__3181776",
    "year": "1775",
    "title": "\"Plan de L'Isle Condor\"",
    "lat": "8.6886",
    "lng": "106.6463"
}