{
    "filename": "hdl%3A1887.1%2Fitem%3A2324889.png",
    "category": "Leiden University Libraries",
    "tags": [
        "Military Fort",
        "Kampong/Village",
        "Road",
        "River",
        "National Border",
        "Colonial Possessions",
        "Mountain/Volcano",
        "Jungle/Wooded Area",
        "Reef",
        "Shoal"
    ],
    "description": "\"Map of Timor with Dutch and Portuguese flags marking military forts. Details are represented pictorially e.g. villages by small houses, forests by trees. There are extensive handwritten annotations, with some text translated from Dutch to French.\"",
    "permalink": "https://historicalmaps.yale-nus.edu.sg/catalog/ld__2324889",
    "year": "1700",
    "title": "\"Groodt Timoor COLLBN 047-24-001\"",
    "lat": "-2.1999",
    "lng": "125.2441"
}