{
    "filename": "nlb__050000120.tif.png",
    "category": "National Library Board Singapore",
    "tags": [
        "Indonesia",
        "Malaysia",
        "Thailand",
        "Vietnam",
        "Cambodia",
        "Laos",
        "Myanmar",
        "Singapore"
    ],
    "description": "\"An early 19th century map, with the regions of Southeast Asia marked with different colours. Interestingly, Cambodia and modern Vietnam (labelled here as Cochinchina and Tonkin) are grouped with China. \"",
    "permalink": "https://maps2.yale-nus.edu.sg/catalog/nlb__050000120",
    "year": "1834",
    "label": "\"Map of the countries between Bengal and China / J. & C. Walker, sculp't.\"",
    "lat": "9.5826",
    "lng": "100.2173"
}