{
    "filename": "nlb__B26056131B.tif.png",
    "category": "National Library Board Singapore",
    "tags": [
        "Southeast Asia",
        "Indonesia",
        "Philippines"
    ],
    "description": "\"This early 19th century map is from a book titled \u2018Mr. John Nieuhoff's Voyages\u2019 in which the author reports on his travels to Southeast Asia, including a detailed description of the important port city of Batavia, as shown on the map.\"",
    "permalink": "https://maps2.yale-nus.edu.sg/catalog/nlb__B26056131B",
    "year": "1810",
    "label": "\"East India islands / J.C. Russell's junior execudit.\"",
    "lat": "5.9312",
    "lng": "114.0381"
}